ansible_workspace/__init__.py
ansible_workspace/__main__.py
ansible_workspace/cli.py
ansible_workspace/git.py
ansible_workspace/misc.py
ansible_workspace/models.py
ansible_workspace/output.py
ansible_workspace/tmuxp.py
ansible_workspace/vscode.py
ansible_workspace-1.0.9.dist-info/LICENSE
ansible_workspace-1.0.9.dist-info/METADATA
ansible_workspace-1.0.9.dist-info/WHEEL
ansible_workspace-1.0.9.dist-info/entry_points.txt
ansible_workspace-1.0.9.dist-info/top_level.txt
ansible_workspace-1.0.9.dist-info/RECORD
