Metadata-Version: 2.1
Name: ansible-workspace
Version: 1.0.9
Summary: Create a workspace for multiple tools to easier develop ansible playbooks with roles.
Home-page: https://github.com/rwxd/ansible_workspace
Author: rwxd
Author-email: rwxd@pm.me
License: MIT
License-File: LICENSE
Requires-Dist: typer ==0.9.0
Requires-Dist: rich ==13.5.2
Requires-Dist: pyyaml ==6.0
